tab/__init__.py
tab/cli.py
tab/exceptions.py
tab/oauth.py
tab/util.py
tabular/__init__.py
tabular/loader.py
tabular/tabular.py
tabulario-0.4.1.dist-info/LICENSE
tabulario-0.4.1.dist-info/METADATA
tabulario-0.4.1.dist-info/WHEEL
tabulario-0.4.1.dist-info/entry_points.txt
tabulario-0.4.1.dist-info/RECORD
