Metadata-Version: 2.1
Name: tabulario
Version: 0.4.1
Summary: Utility library for Tabular.io
Home-page: https://tabular.io/
License: Apache-2.0
Author: Tabular Technologies, Inc.
Author-email: fokko@tabular.io
Requires-Python: >=3.8,<4.0
Classifier: License :: OSI Approved :: Apache Software License
Classifier: Operating System :: OS Independent
Classifier: Programming Language :: Python :: 3
Classifier: Programming Language :: Python :: 3.8
Classifier: Programming Language :: Python :: 3.9
Classifier: Programming Language :: Python :: 3.10
Classifier: Programming Language :: Python :: 3.11
Requires-Dist: click (>=8.1.3,<9.0.0)
Requires-Dist: pyiceberg (==0.4.0)
Requires-Dist: requests (>=2.28.1,<3.0.0)
Project-URL: Repository, https://github.com/tabular-io/
